[{
    "arcana": "Fool",
    "person": "Igor"
},{
    "arcana": "Magician",
    "person": "Morgana"
}, {
    "arcana": "Priestess",
    "person": "Makoto Nijima"
}, {
    "arcana": "Empress",
    "person": "Haru Okumura"
}, {
    "arcana": "Emperor",
    "person": "Yusuke Kitagawa"
}, {
    "arcana": "Hierophant",
    "person": "Sojiro Sakura"
}, {
    "arcana": "Lovers",
    "person": "Ann Takamaki"
}, {
    "arcana": "Chariot",
    "person": "Ryuji Sakamoto"
}, {
    "arcana": "Justice",
    "person": "Goro Akechi"
}, {
    "arcana": "Hermit",
    "person": "Futaba Sakura"
}, {
    "arcana": "Fortune",
    "person": "Chihaya Mifune"
}, {
    "arcana": "Strength",
    "person": "Caroline and Justine"
}, {
    "arcana": "Hanged Man",
    "person": "Munehisa Iwai"
}, {
    "arcana": "Death",
    "person": "Tae Takemi"
}, {
    "arcana": "Temperance",
    "person": "Sadayo Kawakami"
}, {
    "arcana": "Devil",
    "person": "Ichiko Ohya"
}, {
    "arcana": "Tower",
    "person": "Shinya Oda"
}, {
    "arcana": "Star",
    "person": "Hifumi Togo"
}, {
    "arcana": "Moon",
    "person": "Yuuki Mishima"
}, {
    "arcana": "Sun",
    "person": "Toranosuke Yoshida"
}, {
    "arcana": "Judgement",
    "person": "Sae Nijima"
}]